as_dataframe/__init__.py
as_dataframe/main.py
as_dataframe-0.2.2.dist-info/DESCRIPTION.rst
as_dataframe-0.2.2.dist-info/METADATA
as_dataframe-0.2.2.dist-info/RECORD
as_dataframe-0.2.2.dist-info/WHEEL
as_dataframe-0.2.2.dist-info/metadata.json
as_dataframe-0.2.2.dist-info/top_level.txt
